odoo/addons/l10n_th_withholding_tax_report/README.rst
odoo/addons/l10n_th_withholding_tax_report/__init__.py
odoo/addons/l10n_th_withholding_tax_report/__manifest__.py
odoo/addons/l10n_th_withholding_tax_report/data/paper_format.xml
odoo/addons/l10n_th_withholding_tax_report/data/report_data.xml
odoo/addons/l10n_th_withholding_tax_report/i18n/l10n_th_withholding_tax_report.pot
odoo/addons/l10n_th_withholding_tax_report/i18n/th.po
odoo/addons/l10n_th_withholding_tax_report/models/__init__.py
odoo/addons/l10n_th_withholding_tax_report/models/ir_actions_report.py
odoo/addons/l10n_th_withholding_tax_report/models/report_withholding_tax.py
odoo/addons/l10n_th_withholding_tax_report/readme/CONTRIBUTORS.rst
odoo/addons/l10n_th_withholding_tax_report/readme/DESCRIPTION.rst
odoo/addons/l10n_th_withholding_tax_report/readme/HISTORY.rst
odoo/addons/l10n_th_withholding_tax_report/readme/USAGE.rst
odoo/addons/l10n_th_withholding_tax_report/report/__init__.py
odoo/addons/l10n_th_withholding_tax_report/report/report_withholding_tax_qweb.xml
odoo/addons/l10n_th_withholding_tax_report/report/report_withholding_tax_xlsx.py
odoo/addons/l10n_th_withholding_tax_report/static/description/icon.png
odoo/addons/l10n_th_withholding_tax_report/static/description/index.html
odoo/addons/l10n_th_withholding_tax_report/static/src/css/report.css
odoo/addons/l10n_th_withholding_tax_report/static/src/js/withholding_tax_report_backend.js
odoo/addons/l10n_th_withholding_tax_report/static/src/js/withholding_tax_report_widgets.js
odoo/addons/l10n_th_withholding_tax_report/templates/layouts.xml
odoo/addons/l10n_th_withholding_tax_report/templates/report_template.xml
odoo/addons/l10n_th_withholding_tax_report/tests/__init__.py
odoo/addons/l10n_th_withholding_tax_report/tests/date_range_test_data.xml
odoo/addons/l10n_th_withholding_tax_report/tests/test_wt_cert_report.py
odoo/addons/l10n_th_withholding_tax_report/views/menu.xml
odoo/addons/l10n_th_withholding_tax_report/wizard/__init__.py
odoo13_addon_l10n_th_withholding_tax_report-13.0.1.3.0.dist-info/METADATA
odoo13_addon_l10n_th_withholding_tax_report-13.0.1.3.0.dist-info/WHEEL
odoo13_addon_l10n_th_withholding_tax_report-13.0.1.3.0.dist-info/top_level.txt
odoo13_addon_l10n_th_withholding_tax_report-13.0.1.3.0.dist-info/RECORD
